netbox_optics/__init__.py
netbox_optics/choices.py
netbox_optics/constants.py
netbox_optics/filters.py
netbox_optics/forms.py
netbox_optics/models.py
netbox_optics/navigation.py
netbox_optics/tables.py
netbox_optics/template_content.py
netbox_optics/urls.py
netbox_optics/validators.py
netbox_optics/views.py
netbox_optics/api/__init__.py
netbox_optics/api/serializers.py
netbox_optics/api/urls.py
netbox_optics/api/views.py
netbox_optics/migrations/0001_initial.py
netbox_optics/migrations/0002_populate.py
netbox_optics/migrations/0003_on_delete_int.py
netbox_optics/migrations/__init__.py
netbox_optics/templates/netbox_optics/muxwavelengthmap.html
netbox_optics/templates/netbox_optics/opticalconnection.html
netbox_optics/templates/netbox_optics/opticalgrid.html
netbox_optics/templates/netbox_optics/opticalgrid_edit.html
netbox_optics/templates/netbox_optics/opticalgridtype.html
netbox_optics/templates/netbox_optics/opticalgridtype_edit.html
netbox_optics/templates/netbox_optics/opticalgridtypewavelength.html
netbox_optics/templates/netbox_optics/opticalgridtypewavelength_edit.html
netbox_optics/templates/netbox_optics/opticalgridwavelength.html
netbox_optics/templates/netbox_optics/opticalgridwavelength_edit.html
netbox_optics/templates/netbox_optics/opticalspan.html
netbox_optics/templates/netbox_optics/inc/device_mux_port_map.html
netbox_optics/templates/netbox_optics/inc/device_optical_connections.html
netbox_optics/templates/netbox_optics/inc/interface_optical_connection.html
netbox_optics/templatetags/__init__.py
netbox_optics/templatetags/netbox_optics_extras.py
netbox_optics/templatetags/plugin_helpers.py
netbox_optics-0.4.5.dist-info/licenses/LICENSE
netbox_optics-0.4.5.dist-info/METADATA
netbox_optics-0.4.5.dist-info/WHEEL
netbox_optics-0.4.5.dist-info/top_level.txt
netbox_optics-0.4.5.dist-info/RECORD
