Metadata-Version: 2.4
Name: netbox-optics
Version: 0.4.5
Summary: NetBox plugin for modeling Wavelength Division Multiplexing optical connections
Author-email: Konstantin Kudryavtsev <kkudryavtsev@dropbox.com>
License-Expression: Apache-2.0
Keywords: netbox,plugin,optics,wdm,wavelength,dwdm,cwdm
Classifier: Development Status :: 4 - Beta
Classifier: Intended Audience :: Developers
Classifier: Intended Audience :: System Administrators
Classifier: Topic :: System :: Networking
Classifier: Programming Language :: Python :: 3
Classifier: Programming Language :: Python :: 3.10
Classifier: Programming Language :: Python :: 3.11
Classifier: Programming Language :: Python :: 3.12
Classifier: Framework :: Django
Classifier: Framework :: Django :: 4.2
Classifier: Operating System :: OS Independent
Requires-Python: >=3.10
License-File: LICENSE
Provides-Extra: dev
Requires-Dist: pytest>=7.0; extra == "dev"
Requires-Dist: pytest-django>=4.5; extra == "dev"
Requires-Dist: requests>=2.28; extra == "dev"
Requires-Dist: netbox~=3.7.8; extra == "dev"
Requires-Dist: black>=24.0.0; extra == "dev"
Requires-Dist: flake8>=7.0.0; extra == "dev"
Dynamic: license-file
